manifesttool/armbsdiff.cpython-311-aarch64-linux-gnu.so
manifesttool/__init__.py
manifesttool/dev_tool/defaults.py
manifesttool/dev_tool/dev_tool.py
manifesttool/dev_tool/__init__.py
manifesttool/dev_tool/izuma/izuma.py
manifesttool/dev_tool/izuma/__init__.py
manifesttool/dev_tool/actions/update.py
manifesttool/dev_tool/actions/create.py
manifesttool/dev_tool/actions/init.py
manifesttool/dev_tool/actions/code_template.txt
manifesttool/dev_tool/actions/__init__.py
manifesttool/package_tool/package_tool.py
manifesttool/package_tool/package-schema.json
manifesttool/package_tool/__init__.py
manifesttool/package_tool/asn1/package_schema.py
manifesttool/package_tool/asn1/package_encoder.py
manifesttool/package_tool/asn1/__init__.py
manifesttool/package_tool/package_format/package_format.py
manifesttool/package_tool/package_format/tar_package.py
manifesttool/package_tool/package_format/embedded_package.py
manifesttool/package_tool/package_format/__init__.py
manifesttool/package_tool/actions/create.py
manifesttool/package_tool/actions/parse.py
manifesttool/package_tool/actions/__init__.py
manifesttool/common/common_helpers.py
manifesttool/common/__init__.py
manifesttool/mtool/payload_format.py
manifesttool/mtool/mtool.py
manifesttool/mtool/manifest-input-schema.json
manifesttool/mtool/__init__.py
manifesttool/mtool/ecdsa_helper.py
manifesttool/mtool/asn1/manifest_codec.py
manifesttool/mtool/asn1/__init__.py
manifesttool/mtool/asn1/v3/manifest_encoder_v3.py
manifesttool/mtool/asn1/v3/__init__.py
manifesttool/mtool/asn1/v3/manifest_schema_v3.py
manifesttool/mtool/asn1/v1/manifest_schema_v1.py
manifesttool/mtool/asn1/v1/manifest_encoder_v1.py
manifesttool/mtool/asn1/v1/__init__.py
manifesttool/mtool/actions/schema.py
manifesttool/mtool/actions/create.py
manifesttool/mtool/actions/public_key.py
manifesttool/mtool/actions/parse.py
manifesttool/mtool/actions/__init__.py
manifesttool/delta_tool/delta_tool.py
manifest_tool-2.6.2.dist-info/LICENSE
manifest_tool-2.6.2.dist-info/METADATA
manifest_tool-2.6.2.dist-info/entry_points.txt
manifest_tool-2.6.2.dist-info/RECORD
manifest_tool-2.6.2.dist-info/WHEEL
manifest_tool-2.6.2.dist-info/top_level.txt
