Metadata-Version: 2.1
Name: manifest-tool
Version: 2.6.2
Summary: Tool/lib to create and parse manifests
Home-page: https://github.com/PelionIoT/manifest-tool
Author: Izuma Networks
Author-email: opensource@izumanetworks.com
License: Apache 2.0
Requires-Python: >=3.7.0
License-File: LICENSE
Requires-Dist: PyYAML<7.0.0a,>=6.0
Requires-Dist: asn1ate<=0.6.0,>=0.5
Requires-Dist: cryptography==43.0.1
Requires-Dist: jsonschema<=3.2.0,>=2.6.0
Requires-Dist: pyasn1<=0.4.8,>=0.3.1
Requires-Dist: requests==2.32.3
